dms_datastore/__init__.py
dms_datastore/_version.py
dms_datastore/auto_screen.py
dms_datastore/caching.py
dms_datastore/compare_directories.py
dms_datastore/delete_from_filelist.py
dms_datastore/download_cdec.py
dms_datastore/download_cimis.py
dms_datastore/download_dcc.py
dms_datastore/download_des.py
dms_datastore/download_hrrr.py
dms_datastore/download_hycom.py
dms_datastore/download_mokelumne.py
dms_datastore/download_montezuma_gates.py
dms_datastore/download_ncro.py
dms_datastore/download_noaa.py
dms_datastore/download_nwis.py
dms_datastore/download_ucdipm.py
dms_datastore/download_wdl.py
dms_datastore/dropbox_data.py
dms_datastore/dstore_config.py
dms_datastore/filename.py
dms_datastore/hrrr3.py
dms_datastore/inventory.py
dms_datastore/logging_config.py
dms_datastore/populate_repo.py
dms_datastore/prep_header.py
dms_datastore/process_ccfb_gate_height.py
dms_datastore/process_exports.py
dms_datastore/process_flow.py
dms_datastore/process_salt.py
dms_datastore/process_station_variable.py
dms_datastore/process_temp.py
dms_datastore/process_yolo.py
dms_datastore/quarantine.py
dms_datastore/read_multi.py
dms_datastore/read_ts.py
dms_datastore/read_usbr.py
dms_datastore/reformat.py
dms_datastore/screeners.py
dms_datastore/station_info.py
dms_datastore/store_utils.py
dms_datastore/usgs_lookup.py
dms_datastore/usgs_multi.py
dms_datastore/usgs_parameter_cd_query.txt
dms_datastore/write_ts.py
dms_datastore/config_data/compare_excepts_formatted.txt
dms_datastore/config_data/dstore_config.yaml
dms_datastore/config_data/non_15_min_files.txt
dms_datastore/config_data/non_15_min_files_checked.txt
dms_datastore/config_data/realtime_repo.yaml
dms_datastore/config_data/result_aquarius_mapping.csv
dms_datastore/config_data/screen_config_v20230126.yaml
dms_datastore/config_data/screen_regions_v20230126.dbf
dms_datastore/config_data/screen_regions_v20230126.prj
dms_datastore/config_data/screen_regions_v20230126.shp
dms_datastore/config_data/screen_regions_v20230126.shx
dms_datastore-0.4.6.dist-info/METADATA
dms_datastore-0.4.6.dist-info/WHEEL
dms_datastore-0.4.6.dist-info/entry_points.txt
dms_datastore-0.4.6.dist-info/top_level.txt
dms_datastore-0.4.6.dist-info/RECORD
