Metadata-Version: 2.4
Name: dms_datastore
Version: 0.4.6
Summary: Downloading tools and data repository management
Home-page: https://github.com/water-e/dms_datastore
Author: Eli Ateljevich
Author-email: Eli Ateljevich <Eli.Ateljevich@water.ca.gov>, Nicky Sandhu <psandhu@water.ca.gov>
License: MIT
Project-URL: Homepage, https://github.com/water-e/dms_datastore
Keywords: dms_datastore,data,repository,download
Classifier: Development Status :: 4 - Beta
Classifier: Programming Language :: Python :: 3
Requires-Python: <3.14
Requires-Dist: vtools3
Requires-Dist: pyyaml
Requires-Dist: beautifulsoup4
Requires-Dist: tqdm
Requires-Dist: requests
Requires-Dist: lxml
Requires-Dist: openpyxl
Requires-Dist: paramiko
Requires-Dist: pandas>=2
Requires-Dist: numpy
Requires-Dist: xarray
Requires-Dist: dask
Requires-Dist: scikit-learn
Requires-Dist: matplotlib
Requires-Dist: cfgrib
Requires-Dist: diskcache
Requires-Dist: pytest
Requires-Dist: pytest-runner
Provides-Extra: dev
Requires-Dist: pandoc; extra == "dev"
Dynamic: author
Dynamic: home-page
Dynamic: license
